lfquant/__init__.py
lfquant/codebook.py
lfquant-0.0.1.dev4.dist-info/METADATA
lfquant-0.0.1.dev4.dist-info/WHEEL
lfquant-0.0.1.dev4.dist-info/top_level.txt
lfquant-0.0.1.dev4.dist-info/RECORD
