Metadata-Version: 2.1
Name: lfquant
Version: 0.0.1.dev4
Summary: LFQuant - Lookup-Free Quantization
Author: Henry Wu
Keywords: lfquant
Classifier: Programming Language :: Python :: 3
Classifier: Programming Language :: Python :: 3.7
Classifier: Programming Language :: Python :: 3.8
Classifier: Programming Language :: Python :: 3.9
Classifier: Programming Language :: Python :: 3.10
Classifier: Programming Language :: Python :: 3.11
Classifier: Programming Language :: Python :: 3.12
Classifier: Programming Language :: Python :: 3.13
